{
  "_class": "shapePath",
  "booleanOperation": -1,
  "do_objectID": "0F090013-2B98-40F8-8BAB-7CD925E1B425",
  "edited": true,
  "exportOptions": {
    "_class": "exportOptions",
    "do_objectID": "80E47E2A-258A-4496-85BF-445BC80B1B34",
    "exportFormats": [
    ],
    "includedLayerIds": [
    ],
    "layerOptions": 0,
    "shouldTrim": false
  },
  "frame": {
    "_class": "rect",
    "constrainProportions": false,
    "do_objectID": "BB05884B-E31D-4B1F-BEFE-201193A9AD76",
    "height": 2.939583333333332,
    "width": 1.416666666666668,
    "x": 0,
    "y": 0
  },
  "isClosed": true,
  "isFixedToViewport": false,
  "isFlippedHorizontal": false,
  "isFlippedVertical": false,
  "isLocked": false,
  "isVisible": true,
  "layerListExpandedType": 0,
  "name": "Path",
  "nameIsFixed": false,
  "pointRadiusBehaviour": 1,
  "points": [
    {
      "_class": "curvePoint",
      "cornerRadius": 0,
      "curveFrom": "{0.22499999999999998, 1}",
      "curveMode": 2,
      "curveTo": "{0.77499999999999958, 1}",
      "hasCurveFrom": true,
      "hasCurveTo": true,
      "point": "{0.49999999999999933, 1}"
    },
    {
      "_class": "curvePoint",
      "cornerRadius": 0,
      "curveFrom": "{0, 0.75903614457831314}",
      "curveMode": 4,
      "curveTo": "{0, 0.89156626506024106}",
      "hasCurveFrom": false,
      "hasCurveTo": true,
      "point": "{0, 0.75903614457831314}"
    },
    {
      "_class": "curvePoint",
      "cornerRadius": 0,
      "curveFrom": "{0, 0.1084337349397589}",
      "curveMode": 4,
      "curveTo": "{0, 0.24096385542168683}",
      "hasCurveFrom": true,
      "hasCurveTo": false,
      "point": "{0, 0.24096385542168683}"
    },
    {
      "_class": "curvePoint",
      "cornerRadius": 0,
      "curveFrom": "{0.77499999999999958, 0}",
      "curveMode": 2,
      "curveTo": "{0.22499999999999998, 0}",
      "hasCurveFrom": true,
      "hasCurveTo": true,
      "point": "{0.49999999999999933, 0}"
    },
    {
      "_class": "curvePoint",
      "cornerRadius": 0,
      "curveFrom": "{1, 0.24096385542168683}",
      "curveMode": 4,
      "curveTo": "{1, 0.1084337349397589}",
      "hasCurveFrom": false,
      "hasCurveTo": true,
      "point": "{1, 0.24096385542168683}"
    },
    {
      "_class": "curvePoint",
      "cornerRadius": 0,
      "curveFrom": "{1, 0.90361445783132566}",
      "curveMode": 4,
      "curveTo": "{1, 0.77108433734939763}",
      "hasCurveFrom": true,
      "hasCurveTo": false,
      "point": "{1, 0.77108433734939763}"
    }
  ],
  "resizingConstraint": 63,
  "resizingType": 0,
  "rotation": 0,
  "shouldBreakMaskChain": false
}