{
  "_class": "shapeGroup",
  "booleanOperation": -1,
  "clippingMaskMode": 0,
  "do_objectID": "FF70A65F-7EF5-47D5-B830-991B591B416E",
  "exportOptions": {
    "_class": "exportOptions",
    "exportFormats": [
    ],
    "includedLayerIds": [
    ],
    "layerOptions": 0,
    "shouldTrim": false
  },
  "frame": {
    "_class": "rect",
    "constrainProportions": true,
    "height": 16.64583333333334,
    "width": 17,
    "x": 0,
    "y": 0.1770833333333333
  },
  "hasClickThrough": false,
  "hasClippingMask": true,
  "isFixedToViewport": false,
  "isFlippedHorizontal": false,
  "isFlippedVertical": false,
  "isLocked": false,
  "isVisible": true,
  "layerListExpandedType": 1,
  "layers": [
    {
      "class": "shapePath",
      "id": "C0C1EABB-4F7E-43B4-8A0B-9530D75229D9"
    }
  ],
  "name": "Clip 2",
  "nameIsFixed": false,
  "resizingConstraint": 63,
  "resizingType": 0,
  "rotation": 0,
  "shouldBreakMaskChain": false,
  "style": {
    "_class": "style",
    "endMarkerType": 0,
    "miterLimit": 10,
    "startMarkerType": 0,
    "windingRule": 1
  },
  "userInfo": {
    "com.animaapp.stc-sketch-plugin": {
      "kModelPropertiesKey": {
        "constraints": {
          "aspectRatio": {
            "constant": 16.64583,
            "enabled": 1,
            "modelID": "constraint_a539e137-91e2-44ef-b5cf-0de4c0fa24b3",
            "model_class": "ADModelConstraint",
            "model_version": 0.1,
            "multiplier": 17
          },
          "automatic": 1,
          "modelID": "viewConstraints_9a80167d-fc71-4fda-ab9a-6b02e56d26ef",
          "model_class": "ADModelViewConstraints",
          "model_version": 0.1,
          "scaleFactor": 1
        }
      }
    }
  },
  "windingRule": 1
}